mqtt_sn_12-1.0.8.dist-info/licenses/LICENSE
mqttsn12/MqttSnConstants.py
mqttsn12/__init__.py
mqttsn12/mqtt_sn_pub.py
mqttsn12/mqtt_sn_sub.py
mqttsn12/packets.py
mqttsn12/client/MqttSnClient.py
mqttsn12/client/MqttSnClientException.py
mqttsn12/client/__init__.py
mqtt_sn_12-1.0.8.dist-info/METADATA
mqtt_sn_12-1.0.8.dist-info/WHEEL
mqtt_sn_12-1.0.8.dist-info/entry_points.txt
mqtt_sn_12-1.0.8.dist-info/top_level.txt
mqtt_sn_12-1.0.8.dist-info/RECORD
