Metadata-Version: 2.4
Name: mqtt-sn-12
Version: 1.0.8
Summary: Client for protocol MQTT-SN 1.2
Author-email: Marco Ratto <marcoratto@gmail.com>
License-Expression: MIT
Requires-Python: >=3.7
License-File: LICENSE
Dynamic: license-file
